[
 {
  "table":"TADIR",
  "data":
  [
   {
    "PGMID":"R3TR",
    "OBJECT":"PROG",
    "OBJ_NAME":"Y00CARP_ABAPDOC",
    "KORRNUM":"",
    "SRCSYSTEM":"...",
    "AUTHOR":"ABAL",
    "SRCDEP":"",
    "DEVCLASS":"Y00CAPKG_ABAPDOC",
    "GENFLAG":"",
    "EDTFLAG":"",
    "CPROJECT":" S",
    "MASTERLANG":"E",
    "VERSID":"",
    "PAKNOCHECK":"",
    "OBJSTABLTY":"",
    "COMPONENT":"",
    "CRELEASE":"",
    "DELFLAG":"",
    "TRANSLTTXT":"",
    "CREATED_ON":"2021-03-05",
    "CHECK_DATE":"2021-03-05",
    "CHECK_CFG":""
   }
  ]
 },
 {
  "table":"TRDIR",
  "data":
  [
   {
    "NAME":"Y00CARP_ABAPDOC",
    "VARCL":"X",
    "DBAPL":"S",
    "DBNA":"D$",
    "SUBC":"1",
    "APPL":"S",
    "UNAM":"ABAL",
    "RMAND":"010",
    "RLOAD":"E",
    "FIXPT":"X",
    "LDBNAME":"D$S",
    "UCCHECK":"X"
   }
  ]
 },
 {
  "table":"TRDIRT",
  "data":
  [
   {
    "NAME":"Y00CARP_ABAPDOC",
    "SPRSL":"E",
    "TEXT":"ABAPdoc: Generate technical documentation"
   }
  ]
 }
]