[
 {
  "table":"DDTYPES",
  "data":
  [
   {
    "TYPENAME":"Y00CACL_ABAPDOC_CONST",
    "STATE":"A",
    "TYPEKIND":"CLAS"
   }
  ]
 },
 {
  "table":"SEOCLASS",
  "data":
  [
   {
    "CLSNAME":"Y00CACL_ABAPDOC_CONST",
    "CLSTYPE":0,
    "UUID":"QgEKgAATHtufrRkcv6nhCw==",
    "REMOTE":""
   }
  ]
 },
 {
  "table":"SEOCLASSDF",
  "data":
  [
   {
    "CLSNAME":"Y00CACL_ABAPDOC_CONST",
    "VERSION":1,
    "CATEGORY":0,
    "EXPOSURE":2,
    "STATE":1,
    "RELEASE":0,
    "AUTHOR":"ABAL",
    "CREATEDON":"2021-03-05",
    "CHANGEDBY":"",
    "CHANGEDON":"2021-03-05",
    "CHGDANYBY":"",
    "CHGDANYON":"0000-00-00",
    "CLSEMBED":"",
    "CLSABSTRCT":"",
    "CLSFINAL":"X",
    "CLSCCINCL":"X",
    "CLSDEFATT":"",
    "CLSDEFMTD":"",
    "REFCLSNAME":"",
    "FIXPT":"X",
    "VARCL":"",
    "UNICODE":"X",
    "RSTAT":"",
    "CLSBCIMPL":"",
    "R3RELEASE":"755",
    "CLSBCTRANS":"",
    "CLSBCCAT":0,
    "CLSBCNODEL":"",
    "CLSADDON":"",
    "MSG_ID":"",
    "CLSPROXY":"",
    "CLSSHAREDMEMORY":"",
    "WITH_UNIT_TESTS":"",
    "DURATION_TYPE":"0",
    "RISK_LEVEL":"0",
    "WITHIN_PACKAGE":""
   }
  ]
 },
 {
  "table":"SEOCLASSTX",
  "data":
  [
   {
    "CLSNAME":"Y00CACL_ABAPDOC_CONST",
    "LANGU":"E",
    "DESCRIPT":"Constants"
   }
  ]
 },
 {
  "table":"SEOCOMPO",
  "data":
  [
   {
    "CLSNAME":"Y00CACL_ABAPDOC_CONST",
    "CMPNAME":"NAME_CLASS_ROOT",
    "CMPTYPE":0,
    "MTDTYPE":0
   }
  ]
 },
 {
  "table":"SEOCOMPODF",
  "data":
  [
   {
    "CLSNAME":"Y00CACL_ABAPDOC_CONST",
    "CMPNAME":"NAME_CLASS_ROOT",
    "VERSION":1,
    "ALIAS":"",
    "REDEFIN":"",
    "EXPOSURE":2,
    "STATE":1,
    "EDITORDER":1,
    "LOCKED":"",
    "DISPID":0,
    "R3RELEASE":"755",
    "AUTHOR":"ABAL",
    "CREATEDON":"2021-03-05",
    "CHANGEDBY":"",
    "CHANGEDON":"0000-00-00",
    "MTDDECLTYP":0,
    "MTDABSTRCT":"",
    "MTDFINAL":"",
    "DSRNOTEOM":"",
    "EDTX":"",
    "MTDNEWEXC":"",
    "MTDREPLACE":"",
    "MTDOPTNL":"",
    "MTDAMDPRDONLY":"",
    "MTDAMDPCDSCLNT":"",
    "ATTDECLTYP":2,
    "ATTDYNAMIC":"",
    "ATTGETMTD":"",
    "ATTSETMTD":"",
    "ATTRDONLY":"",
    "ATTVALUE":"'Y00CACL_ABAPDOC'",
    "ATTPERSIST":"",
    "ATTBUSOBJ":"",
    "ATTKEYFLD":"",
    "ATTEXPVIRT":0,
    "EVTDECLTYP":0,
    "TYPDUMMY":"",
    "TYPTYPE":1,
    "TYPE":"STRING",
    "TABLEOF":"",
    "SRCROW1":0,
    "SRCCOLUMN1":0,
    "SRCROW2":0,
    "SRCCOLUMN2":0,
    "REFCLSNAME":"",
    "REFINTNAME":"",
    "REFCMPNAME":"",
    "BCMTDINST":"",
    "BCMTDCAT":0,
    "BCMTDDIA":"",
    "BCMTDCOM":"",
    "BCMTDSYN":0,
    "BCEVTCAT":0,
    "TYPESRC_LENG":0,
    "TYPESRC":""
   }
  ]
 },
 {
  "table":"SEOCOMPOTX",
  "data":
  [
   {
    "CLSNAME":"Y00CACL_ABAPDOC_CONST",
    "CMPNAME":"NAME_CLASS_ROOT",
    "LANGU":"E",
    "DESCRIPT":"Root class name"
   }
  ]
 },
 {
  "table":"TADIR",
  "data":
  [
   {
    "PGMID":"R3TR",
    "OBJECT":"CLAS",
    "OBJ_NAME":"Y00CACL_ABAPDOC_CONST",
    "KORRNUM":"",
    "SRCSYSTEM":"...",
    "AUTHOR":"ABAL",
    "SRCDEP":"",
    "DEVCLASS":"Y00CAPKG_ABAPDOC",
    "GENFLAG":"",
    "EDTFLAG":"",
    "CPROJECT":" S",
    "MASTERLANG":"E",
    "VERSID":"",
    "PAKNOCHECK":"",
    "OBJSTABLTY":"",
    "COMPONENT":"",
    "CRELEASE":"",
    "DELFLAG":"",
    "TRANSLTTXT":"",
    "CREATED_ON":"2021-03-05",
    "CHECK_DATE":"2021-03-05",
    "CHECK_CFG":""
   }
  ]
 },
 {
  "table":"TMDIR",
  "data":
  [
   {
    "CLASSNAME":"Y00CACL_ABAPDOC_CONST",
    "METHODINDX":0,
    "METHODNAME":" ",
    "FLAGS":0
   }
  ]
 },
 {
  "table":"TRDIR",
  "data":
  [
   {
    "NAME":"Y00CACL_ABAPDOC_CONST=========CCDEF",
    "DBAPL":"S",
    "DBNA":"D$",
    "SUBC":"I",
    "APPL":"S",
    "UNAM":"ABAL",
    "RMAND":"010",
    "FIXPT":"X",
    "LDBNAME":"D$S",
    "UCCHECK":"X"
   },
   {
    "NAME":"Y00CACL_ABAPDOC_CONST=========CCIMP",
    "DBAPL":"S",
    "DBNA":"D$",
    "SUBC":"I",
    "APPL":"S",
    "UNAM":"ABAL",
    "RMAND":"010",
    "FIXPT":"X",
    "LDBNAME":"D$S",
    "UCCHECK":"X"
   },
   {
    "NAME":"Y00CACL_ABAPDOC_CONST=========CCMAC",
    "DBAPL":"S",
    "DBNA":"D$",
    "SUBC":"I",
    "APPL":"S",
    "UNAM":"ABAL",
    "RMAND":"010",
    "FIXPT":"X",
    "LDBNAME":"D$S",
    "UCCHECK":"X"
   },
   {
    "NAME":"Y00CACL_ABAPDOC_CONST=========CI",
    "DBAPL":"S",
    "DBNA":"D$",
    "SUBC":"I",
    "APPL":"S",
    "UNAM":"ABAL",
    "RMAND":"010",
    "FIXPT":"X",
    "LDBNAME":"D$S",
    "UCCHECK":"X"
   },
   {
    "NAME":"Y00CACL_ABAPDOC_CONST=========CO",
    "DBAPL":"S",
    "DBNA":"D$",
    "SUBC":"I",
    "APPL":"S",
    "UNAM":"ABAL",
    "RMAND":"010",
    "FIXPT":"X",
    "LDBNAME":"D$S",
    "UCCHECK":"X"
   },
   {
    "NAME":"Y00CACL_ABAPDOC_CONST=========CP",
    "EDTX":"X",
    "DBAPL":"S",
    "DBNA":"D$",
    "SUBC":"K",
    "APPL":"S",
    "UNAM":"ABAL",
    "RMAND":"010",
    "FIXPT":"X",
    "LDBNAME":"D$S",
    "UCCHECK":"X"
   },
   {
    "NAME":"Y00CACL_ABAPDOC_CONST=========CT",
    "DBAPL":"S",
    "DBNA":"D$",
    "SUBC":"I",
    "APPL":"S",
    "UNAM":"ABAL",
    "RMAND":"010",
    "FIXPT":"X",
    "LDBNAME":"D$S",
    "UCCHECK":"X"
   },
   {
    "NAME":"Y00CACL_ABAPDOC_CONST=========CU",
    "DBAPL":"S",
    "DBNA":"D$",
    "SUBC":"I",
    "APPL":"S",
    "UNAM":"ABAL",
    "RMAND":"010",
    "FIXPT":"X",
    "LDBNAME":"D$S",
    "UCCHECK":"X"
   }
  ]
 }
]